[{
        "id": 1,
        "name": "jiraffe",
        "introduction": "Long neck",
        "author": "Norisuke",
        "numbers": [
            ["0", "1", "8", "9", "2 3", "1 3", "5", "3", "1", "0"],
            ["1　1", "5", "2", "2", "2", "6", "7", "6", "1　1", "1　1"]
        ],
        "picArray": [
            [0, 0, 1, 0, 1, 0, 0, 0, 0, 0],
            [0, 1, 1, 1, 1, 0, 0, 0, 0, 0],
            [0, 0, 1, 1, 0, 0, 0, 0, 0, 0],
            [0, 0, 1, 1, 0, 0, 0, 0, 0, 0],
            [0, 0, 1, 1, 0, 0, 0, 0, 0, 0],
            [0, 0, 1, 1, 1, 1, 1, 1, 0, 0],
            [0, 0, 1, 1, 1, 1, 1, 1, 1, 0],
            [0, 0, 1, 1, 1, 1, 1, 1, 0, 0],
            [0, 0, 0, 1, 0, 0, 1, 0, 0, 0],
            [0, 0, 0, 1, 0, 0, 1, 0, 0, 0]
        ]
    },
    {
        "id": 2,
        "name": "heart",
        "introduction": "Can't live without this",
        "author": "Norisuke",
        "numbers": [
            ["1 5", "1 4", "1 3", "2 2", "3 1", "3 1", "2 2", "1 3", "1 4", "2 5"],
            ["9", "1　4　1", "2", "0", "0", "1　1", "2　2", "3　3", "4　4", "10"]
        ],
        "picArray": [
            [0, 1, 1, 1, 1, 1, 1, 1, 1, 1],
            [1, 0, 0, 1, 1, 1, 1, 0, 0, 1],
            [0, 0, 0, 0, 1, 1, 0, 0, 0, 0],
            [0, 0, 0, 0, 0, 0, 0, 0, 0, 0],
            [0, 0, 0, 0, 0, 0, 0, 0, 0, 0],
            [1, 0, 0, 0, 0, 0, 0, 0, 0, 1],
            [1, 1, 0, 0, 0, 0, 0, 0, 1, 1],
            [1, 1, 1, 0, 0, 0, 0, 1, 1, 1],
            [1, 1, 1, 1, 0, 0, 1, 1, 1, 1],
            [1, 1, 1, 1, 1, 1, 1, 1, 1, 1]
        ]
    }
]